odoo/addons/report_invoice_modifications/.gitignore
odoo/addons/report_invoice_modifications/CODE_OF_CONDUCT.md
odoo/addons/report_invoice_modifications/__init__.py
odoo/addons/report_invoice_modifications/__manifest__.py
odoo/addons/report_invoice_modifications/views/report_invoice.xml
odoo14_addon_report_invoice_modifications-14.0.0.0.2.dist-info/METADATA
odoo14_addon_report_invoice_modifications-14.0.0.0.2.dist-info/WHEEL
odoo14_addon_report_invoice_modifications-14.0.0.0.2.dist-info/top_level.txt
odoo14_addon_report_invoice_modifications-14.0.0.0.2.dist-info/RECORD
